{"nodes": [{"id": "d_intramap_carto_r_d_mcpiot_nff_cli_mcp_nff_nff_rs_nff_src_commands_install_deps_rs", "label": "install_deps.rs", "file_type": "code", "source_file": "D:\\IntraMap\\Carto\\R_D\\MCPIOT\\nff_cli_mcp\\nff\\nff-rs\\nff\\src\\commands\\install_deps.rs", "source_location": "L1"}, {"id": "commands_install_deps_run", "label": "run()", "file_type": "code", "source_file": "D:\\IntraMap\\Carto\\R_D\\MCPIOT\\nff_cli_mcp\\nff\\nff-rs\\nff\\src\\commands\\install_deps.rs", "source_location": "L5"}, {"id": "installdepsargs", "label": "InstallDepsArgs", "file_type": "code", "source_file": "D:\\IntraMap\\Carto\\R_D\\MCPIOT\\nff_cli_mcp\\nff\\nff-rs\\nff\\src\\commands\\install_deps.rs", "source_location": "L5"}, {"id": "result", "label": "Result", "file_type": "code", "source_file": "D:\\IntraMap\\Carto\\R_D\\MCPIOT\\nff_cli_mcp\\nff\\nff-rs\\nff\\src\\commands\\install_deps.rs", "source_location": "L5"}], "edges": [{"source": "d_intramap_carto_r_d_mcpiot_nff_cli_mcp_nff_nff_rs_nff_src_commands_install_deps_rs", "target": "installdepsargs", "relation": "imports_from", "confidence": "EXTRACTED", "source_file": "D:\\IntraMap\\Carto\\R_D\\MCPIOT\\nff_cli_mcp\\nff\\nff-rs\\nff\\src\\commands\\install_deps.rs", "source_location": "L1", "weight": 1.0, "context": "import"}, {"source": "d_intramap_carto_r_d_mcpiot_nff_cli_mcp_nff_nff_rs_nff_src_commands_install_deps_rs", "target": "installer", "relation": "imports_from", "confidence": "EXTRACTED", "source_file": "D:\\IntraMap\\Carto\\R_D\\MCPIOT\\nff_cli_mcp\\nff\\nff-rs\\nff\\src\\commands\\install_deps.rs", "source_location": "L2", "weight": 1.0, "context": "import"}, {"source": "d_intramap_carto_r_d_mcpiot_nff_cli_mcp_nff_nff_rs_nff_src_commands_install_deps_rs", "target": "result", "relation": "imports_from", "confidence": "EXTRACTED", "source_file": "D:\\IntraMap\\Carto\\R_D\\MCPIOT\\nff_cli_mcp\\nff\\nff-rs\\nff\\src\\commands\\install_deps.rs", "source_location": "L3", "weight": 1.0, "context": "import"}, {"source": "d_intramap_carto_r_d_mcpiot_nff_cli_mcp_nff_nff_rs_nff_src_commands_install_deps_rs", "target": "commands_install_deps_run", "relation": "contains", "confidence": "EXTRACTED", "source_file": "D:\\IntraMap\\Carto\\R_D\\MCPIOT\\nff_cli_mcp\\nff\\nff-rs\\nff\\src\\commands\\install_deps.rs", "source_location": "L5", "weight": 1.0}, {"source": "commands_install_deps_run", "target": "installdepsargs", "relation": "references", "confidence": "EXTRACTED", "source_file": "D:\\IntraMap\\Carto\\R_D\\MCPIOT\\nff_cli_mcp\\nff\\nff-rs\\nff\\src\\commands\\install_deps.rs", "source_location": "L5", "weight": 1.0, "context": "parameter_type"}, {"source": "commands_install_deps_run", "target": "result", "relation": "references", "confidence": "EXTRACTED", "source_file": "D:\\IntraMap\\Carto\\R_D\\MCPIOT\\nff_cli_mcp\\nff\\nff-rs\\nff\\src\\commands\\install_deps.rs", "source_location": "L5", "weight": 1.0, "context": "return_type"}], "raw_calls": [{"caller_nid": "commands_install_deps_run", "callee": "or_else", "is_member_call": true, "source_file": "D:\\IntraMap\\Carto\\R_D\\MCPIOT\\nff_cli_mcp\\nff\\nff-rs\\nff\\src\\commands\\install_deps.rs", "source_location": "L27"}, {"caller_nid": "commands_install_deps_run", "callee": "status", "is_member_call": true, "source_file": "D:\\IntraMap\\Carto\\R_D\\MCPIOT\\nff_cli_mcp\\nff\\nff-rs\\nff\\src\\commands\\install_deps.rs", "source_location": "L31"}, {"caller_nid": "commands_install_deps_run", "callee": "args", "is_member_call": true, "source_file": "D:\\IntraMap\\Carto\\R_D\\MCPIOT\\nff_cli_mcp\\nff\\nff-rs\\nff\\src\\commands\\install_deps.rs", "source_location": "L31"}, {"caller_nid": "commands_install_deps_run", "callee": "success", "is_member_call": true, "source_file": "D:\\IntraMap\\Carto\\R_D\\MCPIOT\\nff_cli_mcp\\nff\\nff-rs\\nff\\src\\commands\\install_deps.rs", "source_location": "L35"}]}